{"remove":{"path":"partition_date=2025-02-21/part-00001-a69700f4-0c44-4a31-b7e2-0fd59bab9593-c000.snappy.parquet","dataChange":true,"deletionTimestamp":1751976057607,"extendedFileMetadata":true,"partitionValues":{"partition_date":"2025-02-21"},"size":3244}}
{"add":{"path":"partition_date=2025-02-22/part-00001-f426c334-3896-460c-b6d9-7acd6fb993bd-c000.snappy.parquet","partitionValues":{"partition_date":"2025-02-22"},"size":3244,"modificationTime":1751976057608,"dataChange":true,"stats":"{\"numRecords\":20,\"minValues\":{\"id\":1,\"title\":\"4K Webcam with Microphone\",\"description\":\"3-foot braided cable with 100W power delivery and data transfer speeds\"},\"maxValues\":{\"title\":\"Wireless Presenter Remote\",\"id\":20,\"description\":\"Waterproof portable speaker with 360-degree sound and 12-hour playback\"},\"nullCount\":{\"description\":0,\"title\":0,\"id\":0}}","tags":null,"baseRowId":null,"defaultRowCommitVersion":null,"clusteringProvider":null}}
{"commitInfo":{"timestamp":1751976057609,"operation":"WRITE","operationParameters":{"mode":"Overwrite","partitionBy":"[\"partition_date\"]"},"clientVersion":"delta-rs.py-1.0.2","operationMetrics":{"execution_time_ms":1,"num_added_files":1,"num_added_rows":20,"num_partitions":0,"num_removed_files":1}}}